Metadata-Version: 2.4
Name: nicegui
Version: 3.6.0
Summary: Create web-based user interfaces with Python. The nice way.
License-Expression: MIT
License-File: LICENSE
Keywords: gui,ui,web,interface,live
Author: Zauberzeug GmbH
Author-email: info@zauberzeug.com
Requires-Python: >=3.9,<4
Classifier: Programming Language :: Python :: 3
Classifier: Programming Language :: Python :: 3.9
Classifier: Programming Language :: Python :: 3.10
Classifier: Programming Language :: Python :: 3.11
Classifier: Programming Language :: Python :: 3.12
Classifier: Programming Language :: Python :: 3.13
Classifier: Programming Language :: Python :: 3.14
Provides-Extra: altair
Provides-Extra: anywidget
Provides-Extra: highcharts
Provides-Extra: matplotlib
Provides-Extra: native
Provides-Extra: plotly
Provides-Extra: redis
Requires-Dist: Pygments (>=2.15.1,<3.0.0)
Requires-Dist: aiofiles (>=23.1.0)
Requires-Dist: aiohttp (>=3.10.2)
Requires-Dist: altair (>=6.0.0) ; extra == "altair"
Requires-Dist: anywidget (>=0.9.21) ; extra == "anywidget"
Requires-Dist: certifi (>=2024.7.4)
Requires-Dist: docutils (>=0.19.0)
Requires-Dist: fastapi (>=0.109.1,!=0.123.5)
Requires-Dist: h11 (>=0.16.0)
Requires-Dist: httpx (>=0.24.0)
Requires-Dist: ifaddr (>=0.2.0)
Requires-Dist: itsdangerous (>=2.1.2,<3)
Requires-Dist: jinja2 (>=3.1.6,<4)
Requires-Dist: markdown2 (>=2.4.7,!=2.4.11)
Requires-Dist: matplotlib (>=3.5.0,<4) ; extra == "matplotlib"
Requires-Dist: nicegui-highcharts (>=2.0.2,<3) ; extra == "highcharts"
Requires-Dist: orjson (>=3.9.15) ; platform_machine != "i386" and platform_machine != "i686" and platform_python_implementation != "PyPy"
Requires-Dist: plotly (>=5.13,<7.0) ; extra == "plotly"
Requires-Dist: pydantic-core (>=2.35.0)
Requires-Dist: python-engineio (>=4.12.0)
Requires-Dist: python-multipart (>=0.0.18)
Requires-Dist: python-socketio[asyncio-client] (>=5.14.0)
Requires-Dist: pywebview (>=5.0.1,<7) ; extra == "native"
Requires-Dist: redis (>=4.0.0) ; extra == "redis"
Requires-Dist: starlette (>=0.49.1)
Requires-Dist: typing-extensions (>=4.0.0)
Requires-Dist: uvicorn[standard] (>=0.22.0)
Requires-Dist: watchfiles (>=0.18.1)
Project-URL: Repository, https://github.com/zauberzeug/nicegui
